aiosocketproto/__init__.py
aiosocketproto/client/__init__.py
aiosocketproto/client/client.py
aiosocketproto/client/methods.py
aiosocketproto/client/processor.py
aiosocketproto/client/send_packet.py
aiosocketproto/client/serializer.py
aiosocketproto/server/__init__.py
aiosocketproto/server/processor.py
aiosocketproto/server/server.py
aiosocketproto-0.0.15.dist-info/LICENSE
aiosocketproto-0.0.15.dist-info/METADATA
aiosocketproto-0.0.15.dist-info/WHEEL
aiosocketproto-0.0.15.dist-info/top_level.txt
aiosocketproto-0.0.15.dist-info/RECORD
